babtools_gentoo.py
setup.py
babtools_gentoo.egg-info/PKG-INFO
babtools_gentoo.egg-info/SOURCES.txt
babtools_gentoo.egg-info/dependency_links.txt
babtools_gentoo.egg-info/top_level.txt