Metadata-Version: 1.1
Name: babtools-gentoo
Version: 0.4.0
Summary: Some tools for the casual Gentoo user and ebuild dabbler. 
Home-page: http://freehg.org/u/ArneBab/babtools_gentoo
Author: Arne Babenhauserheide
Author-email: arne_bab@web.de
License: GNU GPL-3 or later
Keywords: Gentoo,local ebuilds,download and digest ebuilds,convenience
Platform: Any Gentoo
Classifier: License :: OSI Approved :: GNU General Public License (GPL)
Classifier: Programming Language :: Python
Classifier: Operating System :: OS Independent
Classifier: Topic :: Software Development :: Libraries :: Python Modules
Classifier: Intended Audience :: Developers
Classifier: Intended Audience :: End Users/Desktop
Classifier: Environment :: Console
Classifier: Development Status :: 3 - Alpha
Requires: portage
Requires: g_pypi
